{
  "version": "7",
  "dialect": "mysql",
  "entries": [
    {
      "idx": 0,
      "version": "5",
      "when": 1774070826564,
      "tag": "0000_unknown_silhouette",
      "breakpoints": true
    },
    {
      "idx": 1,
      "version": "5",
      "when": 1774094132938,
      "tag": "0001_colossal_titanium_man",
      "breakpoints": true
    },
    {
      "idx": 2,
      "version": "5",
      "when": 1774096775565,
      "tag": "0002_pink_the_liberteens",
      "breakpoints": true
    },
    {
      "idx": 3,
      "version": "5",
      "when": 1774486582149,
      "tag": "0003_watery_albert_cleary",
      "breakpoints": true
    },
    {
      "idx": 4,
      "version": "5",
      "when": 1774541622808,
      "tag": "0004_steep_switch",
      "breakpoints": true
    }
  ]
}